ecojax/core.py
ecojax/register_hydra.py
ecojax/spaces.py
ecojax/time_measure.py
ecojax/types.py
ecojax/utils.py
ecojax/video.py
ecojax/agents/__init__.py
ecojax/agents/base_agent_species.py
ecojax/agents/neuro_evolution.py
ecojax/environment/__init__.py
ecojax/environment/base_env.py
ecojax/environment/gridworld.py
ecojax/evolution/__init__.py
ecojax/evolution/metrics.py
ecojax/evolution/mutator.py
ecojax/loggers/__init__.py
ecojax/loggers/cli.py
ecojax/loggers/csv.py
ecojax/loggers/snakeviz.py
ecojax/loggers/tensorboard.py
ecojax/loggers/wandb.py
ecojax/metrics/__init__.py
ecojax/metrics/aggregators.py
ecojax/metrics/base_aggregators.py
ecojax/metrics/categories.py
ecojax/metrics/utils.py
ecojax/models/__init__.py
ecojax/models/base_model.py
ecojax/models/cnn.py
ecojax/models/mlp.py
ecojax/models/neural_components.py
ecojax/models/random.py
ecojax-1.1.dist-info/LICENSE
ecojax-1.1.dist-info/METADATA
ecojax-1.1.dist-info/WHEEL
ecojax-1.1.dist-info/top_level.txt
ecojax-1.1.dist-info/RECORD
