Metadata-Version: 2.1
Name: ecojax
Version: 1.1
Summary: A framework for simulating ecosystems in JAX.
Home-page: https://github.com/tboulet/EcoJAX
Author: Timothé Boulet
Author-email: timothe.boulet0@gmail.com
License: GNU
License-File: LICENSE
